openplugins/__init__.py
openplugins/assistants/__init__.py
openplugins/assistants/chatgpt_assistants.py
openplugins/data/__init__.py
openplugins/data/manage_data.py
openplugins/openainode/__init__.py
openplugins/openainode/openai_model.py
openplugins/openainode/openai_node.py
openplugins/prompt/__init__.py
openplugins/prompt/few_shot_parameters_generate_prompt.py
openplugins/prompt/few_shot_plan_prompt.py
openplugins/prompt/few_shot_tools_choose_prompt.py
test/__init__.py
test/test_assistant.py
openplugins-0.1.9.dist-info/LICENSE
openplugins-0.1.9.dist-info/METADATA
openplugins-0.1.9.dist-info/WHEEL
openplugins-0.1.9.dist-info/top_level.txt
openplugins-0.1.9.dist-info/RECORD
