Metadata-Version: 2.1
Name: openplugins
Version: 0.1.9
Summary: An open-source project aimed at building an open and diversified ecosystem for chatbot plugins.
Home-page: https://github.com/XingYu-Zhong/Open-ChatGPT-Plugins
Author: XingYu-Zhong
Author-email: zhongxingyuemail@gmail.com
License: MIT
Classifier: License :: OSI Approved :: MIT License
Classifier: Programming Language :: Python
Classifier: Programming Language :: Python :: 3
Classifier: Programming Language :: Python :: 3.6
Classifier: Programming Language :: Python :: Implementation :: CPython
Classifier: Programming Language :: Python :: Implementation :: PyPy
Requires-Python: >=3.6.0
License-File: LICENSE
Requires-Dist: openai
Requires-Dist: pyyaml
Requires-Dist: python-dotenv
Requires-Dist: tokentrim
Requires-Dist: pydantic
Requires-Dist: pytest ==7.4.0
Requires-Dist: pre-commit ==3.3.3
Requires-Dist: pylint ==2.17.4
Requires-Dist: black ==23.3.0
